passpredict/__init__.py
passpredict/__main__.py
passpredict/_rotations.cp310-win_amd64.pyd
passpredict/_solar.cp310-win_amd64.pyd
passpredict/_time.cp310-win_amd64.pyd
passpredict/_version.py
passpredict/caches.py
passpredict/cli.py
passpredict/constants.py
passpredict/exceptions.py
passpredict/geocoding.py
passpredict/locations.py
passpredict/orbit.py
passpredict/solar.py
passpredict/sources.py
passpredict/time.py
passpredict/utils.py
passpredict/observers/__init__.py
passpredict/observers/brute_force.py
passpredict/observers/core.py
passpredict/observers/functions.py
passpredict/observers/observer.py
passpredict/observers/orbit_predictor.py
passpredict/satellites/__init__.py
passpredict/satellites/base.py
passpredict/satellites/kepler.py
passpredict/satellites/sgp4.py
passpredict-0.5.1.dist-info/LICENSE
passpredict-0.5.1.dist-info/METADATA
passpredict-0.5.1.dist-info/WHEEL
passpredict-0.5.1.dist-info/entry_points.txt
passpredict-0.5.1.dist-info/top_level.txt
passpredict-0.5.1.dist-info/RECORD
