Metadata-Version: 2.1
Name: passpredict
Version: 0.5.1
Summary: Predict upcoming satellite overpasses
Home-page: https://www.github.com/samtx/passpredict
Author: Sam Friedman
License: MIT
Keywords: iss predict orbit sgp4 satellite
Classifier: License :: OSI Approved :: Python Software Foundation License
Classifier: Programming Language :: Python :: 3
Classifier: Programming Language :: Python :: 3.8
Classifier: Programming Language :: Python :: 3.9
Classifier: Programming Language :: Python :: 3.10
Requires-Python: >=3.8
License-File: LICENSE
Requires-Dist: sgp4 (>=2.12)
Requires-Dist: numpy (>=1.22)
Requires-Dist: scipy
Requires-Dist: orbit-predictor
Requires-Dist: click
Requires-Dist: rich
Requires-Dist: httpx
Requires-Dist: timezonefinder
Requires-Dist: tzdata ; platform_system == "Windows"
Requires-Dist: backports.zoneinfo ; python_version < "3.9"
Provides-Extra: dev
Requires-Dist: Cython (>=0.29.24) ; extra == 'dev'
Requires-Dist: pytest (>=6.2.5) ; extra == 'dev'
Requires-Dist: pytest-html ; extra == 'dev'
Requires-Dist: pytest-cov ; extra == 'dev'
Requires-Dist: flake8 ; extra == 'dev'
Provides-Extra: docs
Requires-Dist: mkdocs-material ; extra == 'docs'
Requires-Dist: mkdocstrings ; extra == 'docs'
Requires-Dist: pytkdocs[numpy-style] ; extra == 'docs'
